kegg2svg/__init__.py
kegg2svg/cli.py
kegg2svg/colors.csv
kegg2svg/kegg2svg.py
kegg2svg-0.4.8.dist-info/METADATA
kegg2svg-0.4.8.dist-info/WHEEL
kegg2svg-0.4.8.dist-info/entry_points.txt
kegg2svg-0.4.8.dist-info/top_level.txt
kegg2svg-0.4.8.dist-info/RECORD
